{
  "template_id": "96aa03f7-88ed-4b4f-bf16-92e061de9ffb",
  "name": "Endsem_template_updated.docx",
  "docx_path": "backend\\Storage\\templates\\user_3A0hhvVYuctXx5uxz85ScNsHGk5\\96aa03f7-88ed-4b4f-bf16-92e061de9ffb_Endsem_template_updated.docx",
  "pattern": [
    {
      "question_num": 1,
      "parts": [
        "a",
        "b",
        "c",
        "d"
      ],
      "num_parts": 4,
      "marks_per_part": 5
    },
    {
      "question_num": 2,
      "parts": [
        "a",
        "b"
      ],
      "num_parts": 2,
      "marks_per_part": 10
    },
    {
      "question_num": 3,
      "parts": [
        "a",
        "b"
      ],
      "num_parts": 2,
      "marks_per_part": 10
    },
    {
      "question_num": 4,
      "parts": [
        "a",
        "b"
      ],
      "num_parts": 2,
      "marks_per_part": 10
    },
    {
      "question_num": 5,
      "parts": [
        "a",
        "b"
      ],
      "num_parts": 2,
      "marks_per_part": 10
    },
    {
      "question_num": 6,
      "parts": [
        "a",
        "b"
      ],
      "num_parts": 2,
      "marks_per_part": 10
    }
  ],
  "placeholders": [
    "[10]",
    "[1a]",
    "[1b]",
    "[1c]",
    "[1d]",
    "[2a]",
    "[2b]",
    "[3a]",
    "[3b]",
    "[4a]",
    "[4b]",
    "[5]",
    "[5a]",
    "[5b]",
    "[6a]",
    "[6b]",
    "[SUBJECT]",
    "[duration]",
    "[marks]",
    "[subject]"
  ],
  "azure_url": "https://qpilotstorage1.blob.core.windows.net/qpilot-templates/templates/user_3A0hhvVYuctXx5uxz85ScNsHGk5/96aa03f7-88ed-4b4f-bf16-92e061de9ffb/Endsem_template_updated.docx"
}